btormiter.py
btor2_opt-0.3.0.dist-info/licenses/LICENSE
btoropt/__init__.py
btoropt/__main__.py
btoropt/modparser.py
btoropt/parser.py
btoropt/program.py
btoropt/passes/allpasses.py
btoropt/passes/genericpass.py
btoropt/passes/transforms/initAllStates.py
btoropt/passes/transforms/renameInputs.py
btoropt/passes/validation/checkLidOrdering.py
btor2_opt-0.3.0.dist-info/METADATA
btor2_opt-0.3.0.dist-info/WHEEL
btor2_opt-0.3.0.dist-info/entry_points.txt
btor2_opt-0.3.0.dist-info/top_level.txt
btor2_opt-0.3.0.dist-info/RECORD
