Metadata-Version: 2.4
Name: btor2-opt
Version: 0.3.0
Summary: Very basic btor2 parser, circuit miter, and code optimizer.
Author-email: Amelia Dobis <ad4048@princeton.edu>
License:                     GNU GENERAL PUBLIC LICENSE
Project-URL: repository, https://github.com/dobios/btoropt
Keywords: btor2,parser,compiler
Classifier: License :: OSI Approved :: GNU General Public License v3 (GPLv3)
Classifier: Programming Language :: Python
Classifier: Programming Language :: Python :: 3
Requires-Python: >=3.10
License-File: LICENSE
Requires-Dist: tqdm>=4.67.1
Provides-Extra: dev
Requires-Dist: black; extra == "dev"
Requires-Dist: bumpver; extra == "dev"
Requires-Dist: isort; extra == "dev"
Requires-Dist: pip-tools; extra == "dev"
Dynamic: license-file
